example_package_abcd/__init__.py
example_package_abcd/example.py
example_package_abcd/hello.py
example_package_abcd-0.0.2.dist-info/METADATA
example_package_abcd-0.0.2.dist-info/WHEEL
example_package_abcd-0.0.2.dist-info/entry_points.txt
example_package_abcd-0.0.2.dist-info/licenses/LICENSE
example_package_abcd-0.0.2.dist-info/RECORD
